rose_ai/__init__.py
rose_ai/main.py
RoseAI-1.0.0.dist-info/METADATA
RoseAI-1.0.0.dist-info/WHEEL
RoseAI-1.0.0.dist-info/top_level.txt
RoseAI-1.0.0.dist-info/RECORD
